<?xml version="1.0" encoding="UTF-8"?>
<SubmitSMSReq>
   <MsgType>SubmitSMSReq</MsgType>
   <Version>1.0.0</Version>
   <Send_Address>
           <Address_Info>
                   <DeviceType>203</DeviceType>
                   <DeviceID>PWWW</DeviceID>
           </Address_Info>
   </Send_Address>
   <Dest_Address>
           <Address_Info>
                   <DeviceType>200</DeviceType>
                   <DeviceID>CSS</DeviceID>
           </Address_Info>
   </Dest_Address>
   <SPID>905237</SPID>
   <SPServiceID>001DXMH001</SPServiceID>
   <Senders>
           <Msg_Address>
                   <AddressType>3</AddressType>
                   <ClassType>1</ClassType>
                   <Address>10658666</Address>
           </Msg_Address>
   </Senders>
   <Recipients>
           <Msg_Address>
                   <AddressType>1</AddressType>
                   <ClassType>1</ClassType>
                   <Address>13753164014</Address>
           </Msg_Address>
   </Recipients>
   <ChargedParty>2</ChargedParty>
   <ChargedPartyID>
           <Msg_Address>
                   <AddressType>1</AddressType>
                   <ClassType>1</ClassType>
                   <Address>13753164014</Address>
           </Msg_Address>
   </ChargedPartyID>
   <CPCode/>
   <ContentID/>
	<Content_info>
	    <SMS_Content_Info>
	         <MsgFmt>15</MsgFmt>
			 <!--${weixinAppNameView}、${context}表示动态验证码，不能省略，其它文字可以修改-->
			<BindMsisdnData>尊敬的用户，您的手机号将与微信服务号${weixinAppNameView}进行绑定，绑定密码为${context}，5分钟内有效。</BindMsisdnData>
			<GetSubFolwRedData>尊敬的用户，微信服务号${weixinAppNameView}赠送流量红包的动态密码为${context}，5分钟内有效。</GetSubFolwRedData>
		</SMS_Content_Info>
	</Content_info>
	<LinkID/>
</SubmitSMSReq>